thumber/__init__.py
thumber/main.py
thumber-0.3.1.dist-info/licenses/LICENSE
thumber-0.3.1.dist-info/METADATA
thumber-0.3.1.dist-info/WHEEL
thumber-0.3.1.dist-info/entry_points.txt
thumber-0.3.1.dist-info/top_level.txt
thumber-0.3.1.dist-info/RECORD
