Metadata-Version: 2.4
Name: thumber
Version: 0.3.1
Summary: Create thumbnails. Specify dimensions or aspect ratio.
Author: veralvx
Maintainer: veralvx
Project-URL: Homepage, https://github.com/veralvx/thumber
Project-URL: Repository, https://github.com/veralvx/thumber.git
Project-URL: Issues, https://github.com/veralvx/thumber/issues
Project-URL: Mastodon, https://mastodon.social/@veralvx
Project-URL: Twitter, https://x.com/veralvx
Project-URL: Changelog, https://github.com/veralvx/thumber/blob/main/CHANGELOG.md
Keywords: thumbnail,image,filter,ratio,aspect ratio,crop
Classifier: Programming Language :: Python :: 3
Classifier: Programming Language :: Python :: 3.9
Classifier: Programming Language :: Python :: 3.10
Classifier: Programming Language :: Python :: 3.11
Classifier: Programming Language :: Python :: 3.12
Classifier: Programming Language :: Python :: 3.13
Classifier: Programming Language :: Python :: 3.14
Classifier: Programming Language :: Python
Classifier: Environment :: Console
Classifier: Intended Audience :: Developers
Classifier: License :: OSI Approved :: MIT License
Classifier: Natural Language :: English
Requires-Python: >=3.9
License-File: LICENSE
Requires-Dist: pillow<13.0,>=11.1.0
Dynamic: license-file
